nbreport/__init__.py
nbreport/compute.py
nbreport/instance.py
nbreport/processing.py
nbreport/repo.py
nbreport/templating.py
nbreport/userconfig.py
nbreport/cli/__init__.py
nbreport/cli/compute.py
nbreport/cli/init.py
nbreport/cli/issue.py
nbreport/cli/login.py
nbreport/cli/main.py
nbreport/cli/register.py
nbreport/cli/render.py
nbreport/cli/test.py
nbreport/cli/upload.py
nbreport-0.7.4.dist-info/LICENSE
nbreport-0.7.4.dist-info/METADATA
nbreport-0.7.4.dist-info/WHEEL
nbreport-0.7.4.dist-info/entry_points.txt
nbreport-0.7.4.dist-info/top_level.txt
nbreport-0.7.4.dist-info/RECORD
