Metadata-Version: 2.1
Name: nbreport
Version: 0.7.4
Summary: LSST's notebook-based report system.
Home-page: https://github.com/lsst-sqre/nbreport
Author: Association of Universities for Research in Astronomy
Author-email: jsick@lsst.org
License: MIT
Keywords: lsst
Platform: UNKNOWN
Classifier: Development Status :: 4 - Beta
Classifier: License :: OSI Approved :: MIT License
Classifier: Programming Language :: Python :: 3.6
Requires-Dist: click
Requires-Dist: cookiecutter (<2.0.0,>=1.6.0)
Requires-Dist: nbformat
Requires-Dist: nbconvert
Requires-Dist: jupyter
Requires-Dist: ruamel.yaml (<0.16.0,>=0.15.0)
Requires-Dist: GitPython
Requires-Dist: requests (>=2.0)
Provides-Extra: dev
Requires-Dist: documenteer[pipelines] (<0.6.0,>=0.5.0) ; extra == 'dev'
Requires-Dist: sphinx-click ; extra == 'dev'
Requires-Dist: pytest (==5.0.1) ; extra == 'dev'
Requires-Dist: pytest-cov (==2.7.1) ; extra == 'dev'
Requires-Dist: pytest-flake8 (==1.0.4) ; extra == 'dev'
Requires-Dist: responses (==0.10.6) ; extra == 'dev'
